MANIFEST.in
requirements.txt
setup.cfg
setup.py
framepy/__init__.py
framepy/_configuration.py
framepy/_method_inspection.py
framepy/_thread_level_cache.py
framepy/_utils.py
framepy/amqp.py
framepy/aws.py
framepy/beans.py
framepy/client.py
framepy/core.py
framepy/db.py
framepy/eureka.py
framepy/logs.py
framepy/modules.py
framepy/redisdb.py
framepy/testing.py
framepy/web.py
framepy.egg-info/PKG-INFO
framepy.egg-info/SOURCES.txt
framepy.egg-info/dependency_links.txt
framepy.egg-info/requires.txt
framepy.egg-info/top_level.txt