Metadata-Version: 1.1
Name: framepy
Version: 3.58
Summary: Very simple web application framework with support for AMQP and DI
Home-page: https://github.com/mkorman9/framepy
Author: Michal Korman
Author-email: m.korman94@gmail.com
License: UNKNOWN
Download-URL: https://github.com/mkorman9/framepy/tarball/3.58
Keywords: web,framework,amqp,di,db
Platform: UNKNOWN
